agents/__init__.py
agents/elegantrl_models.py
agents/elegantrl_models_wt.py
agents/rllib_models.py
agents/stablebaselines3_models.py
meta/__init__.py
meta/config.py
meta/config_tickers.py
meta/data_processor.py
meta/data_processors/__init__.py
meta/data_processors/_base.py
meta/data_processors/alpaca.py
meta/data_processors/baostock.py
meta/data_processors/binance.py
meta/data_processors/ccxt.py
meta/data_processors/fx.py
meta/data_processors/iexcloud.py
meta/data_processors/joinquant.py
meta/data_processors/quandl.py
meta/data_processors/quantconnect.py
meta/data_processors/ricequant.py
meta/data_processors/tushare.py
meta/data_processors/wrds.py
meta/data_processors/yahoofinance.py
meta/env_fx_trading/__init__.py
meta/env_fx_trading/env_fx.py
finrl_meta-0.3.5.dist-info/LICENSE
finrl_meta-0.3.5.dist-info/METADATA
finrl_meta-0.3.5.dist-info/WHEEL
finrl_meta-0.3.5.dist-info/top_level.txt
finrl_meta-0.3.5.dist-info/RECORD
