Metadata-Version: 2.1
Name: finrl-meta
Version: 0.3.5
Summary: FinRL­-Meta: A Universe of ­ Market En­vironments for Data­-Driven Financial Reinforcement Learning
Home-page: https://github.com/AI4Finance-Foundation/FinRL-Meta
Author: Xiaoyang Liu, Ming Zhu, Jingyang Rui, Hongyang Yang
Author-email: hy2500@columbia.edu
License: MIT
Keywords: Reinforcment Learning
Platform: UNKNOWN
Classifier: License :: OSI Approved :: MIT License
Classifier: Programming Language :: Python
Classifier: Programming Language :: Python :: 3
Classifier: Programming Language :: Python :: 3.6
Classifier: Programming Language :: Python :: 3.7
Classifier: Programming Language :: Python :: 3.8
Classifier: Programming Language :: Python :: 3.9
Classifier: Programming Language :: Python :: 3.10
Classifier: Programming Language :: Python :: Implementation :: CPython
Classifier: Programming Language :: Python :: Implementation :: PyPy
Requires-Python: >=3.6
License-File: LICENSE
Requires-Dist: alpaca-trade-api (>=2.1.0)
Requires-Dist: ccxt (==1.90.41)
Requires-Dist: elegantrl
Requires-Dist: exchange-calendars (==4.1.1)
Requires-Dist: gputil (==1.4.0)
Requires-Dist: gym (==0.24.1)
Requires-Dist: jqdatasdk (==1.8.10)
Requires-Dist: lz4 (==4.0.1)
Requires-Dist: matplotlib (==3.5.2)
Requires-Dist: numpy (==1.23.1)
Requires-Dist: pandas (==1.4.3)
Requires-Dist: pandas-market-calendars (==3.5)
Requires-Dist: pre-commit (==2.19.0)
Requires-Dist: pytest (==7.1.2)
Requires-Dist: ray[default] (==1.13.0)
Requires-Dist: scikit-learn (==1.1.1)
Requires-Dist: setuptools (==63.1.0)
Requires-Dist: stable-baselines3[extra] (==1.5.0)
Requires-Dist: stockstats (==0.4.1)
Requires-Dist: tensorboardX (==2.5.1)
Requires-Dist: vectorbt[full] (==0.23.3)
Requires-Dist: wheel (==0.37.1)
Requires-Dist: wrds (==3.1.1)
Requires-Dist: yfinance (==0.1.72)
